   [{
	"id":1,
	"text":"客户关系管理系统",
	"children":[{
		"id":11,
		"text":"营销管理",
		"children":[{
			"id":111,
			"text":"销售机会管理",
			"attributes":{    
	            "url":"/crm-1/chance/list" 
	        }
		},{
			"id":112,
			"text":"客户开发计划",
			"attributes":{    
	            "url":"/crm-1/plan/chance/list" 
	        }
		}]
	},{
		"id":12,
		"text":"客户管理",
		"children":[{
			"id":121,
			"text":"客户信息管理",
			"attributes":{    
	            "url":"/c.html" 
	        }
		},{
			"id":122,
			"text":"客户流失管理",
			"attributes":{
				"url":"/d.html"
			}
		}]
	},{
		"id":13,
		"text":"服务管理",
		"children":[{
			"id":131,
			"text":"服务创建",
			"attributes":{
				"url":"/e.html"
			}
		},{
			"id":132,
			"text":"服务分配",
			"attributes":{
				"url":"/f.html"
			}
		},{
			"id":133,
			"text":"服务处理",
			"attributes":{
				"url":"/g.html"
			}
		},{
			"id":134,
			"text":"服务反馈",
			"attributes":{
				"url":"/h.html"
			}
		},{
			"id":135,
			"text":"服务归档",
			"attributes":{
				"url":"/i.html"
			}
		}]
	},{
		"id":14,
		"text":"统计报表",
		"children":[{
			"id":141,
			"text":"客户贡献风险",
			"attributes":{
				"url":"/j.html"
			}
		},{
			"id":142,
			"text":"客户构成分析",
			"attributes":{
				"url":"/k.html"
			}
		},{
			"id":143,
			"text":"客户服务分析",
			"attributes":{
				"url":"/l.html"
			}
		},{
			"id":144,
			"text":"客户流失分析",
			"attributes":{
				"url":"/m.html"
			}
		}]
	},{
		"id":15,
		"text":"基础数据",
		"children":[{
			"id":151,
			"text":"数据字典管理",
			"attributes":{
				"url":"/n.html"
			}
		},{
			"id":152,
			"text":"查询产品信息",
			"attributes":{
				"url":"/n.html"
			}
		},{
			"id":153,
			"text":"查询库存信息",
			"attributes":{
				"url":"/crm-1/storage/list" 
			}
		}]
	},{
		"id":16,
		"text":"系统权限管理",
		"children":[{
			"id":161,
			"text":"系统用户管理",
			"attributes":{
				"url":"/p.html"
			}
		},{
			"id":162,
			"text":"角色管理",
			"attributes":{
				"url":"/q.html"
			}
		}]
	}]
}]
